onedrive/__init__.py
onedrive/__main__.py
onedrive/algorithms.py
onedrive/cli.py
onedrive/database.py
onedrive/local.py
onedrive/model.py
onedrive/platform.py
onedrive/quickxor.py
onedrive/sdk.py
onedrive/sync.py
onedrive_sync_client-0.2.4.dist-info/METADATA
onedrive_sync_client-0.2.4.dist-info/RECORD
onedrive_sync_client-0.2.4.dist-info/WHEEL
onedrive_sync_client-0.2.4.dist-info/entry_points.txt
onedrive_sync_client-0.2.4.dist-info/top_level.txt
