Metadata-Version: 2.1
Name: onedrive-sync-client
Version: 0.2.4
Summary: OneDrive Client with Two-way Synchronizing Feature
Home-page: https://github.com/gzxu/onedrive-sync-client
Author: XU Guang-zhao
License: AGPL-3.0-only
Project-URL: Source Code, https://github.com/gzxu/onedrive-sync-client
Project-URL: Bug Tracker, https://github.com/gzxu/onedrive-sync-client/issues
Keywords: onedrive sync
Platform: UNKNOWN
Classifier: Development Status :: 3 - Alpha
Classifier: Environment :: Console
Classifier: Intended Audience :: End Users/Desktop
Classifier: Intended Audience :: Developers
Classifier: License :: OSI Approved :: GNU Affero General Public License v3
Classifier: Programming Language :: Python :: 3.5
Classifier: Programming Language :: Python :: 3.6
Classifier: Programming Language :: Python :: 3.7
Classifier: Topic :: Office/Business :: Office Suites
Classifier: Topic :: Utilities
Requires-Python: >=3.5
Requires-Dist: attrs (==18.1.0)
Requires-Dist: certifi (==2018.4.16)
Requires-Dist: chardet (==3.0.4)
Requires-Dist: idna (==2.6)
Requires-Dist: meson (==0.46.0)
Requires-Dist: oauthlib (==2.1.0)
Requires-Dist: requests (==2.18.4)
Requires-Dist: requests-oauthlib (==1.0.0)
Requires-Dist: SQLAlchemy (==1.2.8)
Requires-Dist: urllib3 (==1.22)
